{"width":512,"imagePath":"fish_4002_tex.png","height":1024,"name":"fish_4002","SubTexture":[{"width":245,"y":1,"height":135,"name":"fish250002.png","x":1},{"frameHeight":135,"y":138,"frameX":-5,"width":240,"frameY":-4,"height":127,"name":"fish250004.png","frameWidth":245,"x":1},{"frameHeight":135,"y":617,"frameX":-6,"width":239,"frameY":-9,"height":113,"name":"fish250010.png","frameWidth":245,"x":1},{"frameHeight":135,"y":269,"frameX":0,"width":245,"frameY":-10,"height":115,"name":"fish250012.png","frameWidth":245,"x":244},{"frameHeight":135,"y":267,"frameX":-4,"width":241,"frameY":-9,"height":117,"name":"fish250005.png","frameWidth":245,"x":1},{"frameHeight":135,"y":502,"frameX":-4,"width":241,"frameY":-9,"height":113,"name":"fish250011.png","frameWidth":245,"x":1},{"frameHeight":135,"y":134,"frameX":-4,"width":241,"frameY":-1,"height":133,"name":"fish250003.png","frameWidth":245,"x":248},{"frameHeight":135,"y":386,"frameX":0,"width":245,"frameY":-11,"height":114,"name":"fish250007.png","frameWidth":245,"x":1},{"frameHeight":135,"y":616,"frameX":-4,"width":241,"frameY":-9,"height":113,"name":"fish250009.png","frameWidth":245,"x":244},{"frameHeight":135,"y":501,"frameX":-1,"width":243,"frameY":-10,"height":113,"name":"fish250008.png","frameWidth":245,"x":248},{"frameHeight":135,"y":1,"frameX":0,"width":245,"frameY":-2,"height":131,"name":"fish250001.png","frameWidth":245,"x":248},{"frameHeight":135,"y":386,"frameX":-1,"width":243,"frameY":-12,"height":113,"name":"fish250006.png","frameWidth":245,"x":248}]}