{
    "11401": "hqtpb.shuiguoji.ScShuiguojiPlayerInfoNotify",
    "11402": "hqtpb.shuiguoji.ScShuiguojiOnlineCountNotify",
    "11403": "hqtpb.shuiguoji.ScShuiguojiIssueNotify",
    "11404": "hqtpb.shuiguoji.ScShuiguojiStateNotify",
    "11405": "hqtpb.shuiguoji.ScShuiguojiLimitNotify",
    "11406": "hqtpb.shuiguoji.CsShuiguojiBetReq",
    "11407": "hqtpb.shuiguoji.ScShuiguojiBetRes",
    "11408": "hqtpb.shuiguoji.ScShuiguojiPlayerBetInfoNotify",
    "11409": "hqtpb.shuiguoji.ScShuiguojiGameBetInfoNotify",
    "11410": "hqtpb.shuiguoji.ScShuiguojiGameResultNotify",
    "11411": "hqtpb.shuiguoji.CsShuiguojiChartReq",
    "11412": "hqtpb.shuiguoji.ScShuiguojiChartRes",
    "11413": "hqtpb.shuiguoji.CsShuiguojiRankingListReq",
    "11414": "hqtpb.shuiguoji.ScShuiguojiRankingListRes",
    "11415": "hqtpb.shuiguoji.ScShuiguojiSpecialPlayerNotify",
    "11416": "hqtpb.shuiguoji.SCShuiguojiSpecialPlayerActionNotify",
    "11417": "hqtpb.shuiguoji.CsShuiguojiCancelBetReq",
    "11418": "hqtpb.shuiguoji.ScShuiguojiCancelBetRes",
    "11419": "hqtpb.shuiguoji.ScShuiguojiLastBetNotify",
    "11420": "hqtpb.shuiguoji.ScShuiguojiBaseBetNotify",
    "11421": "hqtpb.shuiguoji.CsShuiguojiStateReq",
    "11422": "hqtpb.shuiguoji.ScShuiguojiStateRes"
}