{"width":256,"imagePath":"star_0_tex.png","height":256,"name":"star_0","SubTexture":[{"y":1,"frameX":-4,"frameHeight":64,"frameY":-2,"width":57,"frameWidth":64,"height":52,"name":"补间 15","x":127},{"y":61,"frameX":-26,"frameHeight":64,"frameY":-14,"width":12,"frameWidth":64,"height":41,"name":"补间 22","x":113},{"y":157,"frameX":-6,"frameHeight":64,"frameY":-8,"width":35,"frameWidth":64,"height":47,"name":"补间 21","x":113},{"y":1,"frameX":-3,"frameHeight":64,"frameY":0,"width":61,"frameWidth":64,"height":61,"name":"补间 13","x":1},{"y":54,"frameX":-4,"frameHeight":64,"frameY":-4,"width":54,"frameWidth":64,"height":51,"name":"补间 16","x":186},{"y":108,"frameX":-6,"frameHeight":64,"frameY":-9,"width":38,"frameWidth":64,"height":47,"name":"补间 20","x":113},{"y":1,"frameX":-3,"frameHeight":64,"frameY":0,"width":61,"frameWidth":64,"height":58,"name":"补间 14","x":64},{"y":64,"frameX":-26,"frameHeight":64,"frameY":-26,"width":18,"frameWidth":64,"height":17,"name":"补间 9","x":36},{"y":64,"frameX":-16,"frameHeight":64,"frameY":-18,"width":33,"frameWidth":64,"height":33,"name":"补间 10","x":1},{"y":1,"frameX":-3,"frameHeight":64,"frameY":-9,"width":55,"frameWidth":64,"height":51,"name":"补间 12","x":186},{"y":107,"frameX":-6,"frameHeight":64,"frameY":-10,"width":49,"frameWidth":64,"height":49,"name":"补间 11","x":179},{"y":61,"frameX":-4,"frameHeight":64,"frameY":-7,"width":47,"frameWidth":64,"height":49,"name":"补间 18","x":64},{"y":55,"frameX":-4,"frameHeight":64,"frameY":-5,"width":50,"frameWidth":64,"height":51,"name":"补间 17","x":127},{"y":108,"frameX":-5,"frameHeight":64,"frameY":-8,"width":43,"frameWidth":64,"height":48,"name":"补间 19","x":1}]}