{"width":4096,"height":2048,"name":"CardBone_7","imagePath":"CardBone_7_tex.png","SubTexture":[{"frameHeight":592,"y":1,"frameWidth":576,"frameX":0,"width":576,"frameY":-80,"height":292,"name":"spring0019.png","x":1735},{"frameHeight":592,"y":1,"frameWidth":576,"frameX":0,"width":576,"frameY":-80,"height":292,"name":"spring0021.png","x":2313},{"frameHeight":592,"y":1213,"frameWidth":576,"frameX":0,"width":576,"frameY":-74,"height":298,"name":"spring0017.png","x":1},{"frameHeight":592,"y":295,"frameWidth":576,"frameX":0,"width":576,"frameY":-84,"height":288,"name":"spring0009.png","x":1735},{"frameHeight":592,"y":1807,"frameWidth":576,"frameX":-70,"width":451,"frameY":-94,"height":228,"name":"spring0003.png","x":1},{"frameHeight":592,"y":577,"frameWidth":576,"frameX":0,"width":575,"frameY":-86,"height":277,"name":"spring0007.png","x":3469},{"frameHeight":592,"y":1,"frameWidth":576,"frameX":0,"width":576,"frameY":-80,"height":292,"name":"spring0022.png","x":2891},{"width":576,"y":1,"height":592,"name":"spring0029.png","x":1},{"frameHeight":592,"y":1757,"frameWidth":576,"frameX":0,"width":576,"frameY":-83,"height":289,"name":"spring0014.png","x":579},{"frameHeight":592,"y":1,"frameWidth":576,"frameX":0,"width":576,"frameY":-80,"height":292,"name":"spring0020.png","x":1157},{"frameHeight":592,"y":295,"frameWidth":576,"frameX":0,"width":576,"frameY":-80,"height":292,"name":"spring0023.png","x":579},{"frameHeight":592,"y":585,"frameWidth":576,"frameX":-56,"width":481,"frameY":-80,"height":257,"name":"spring0004.png","x":1157},{"frameHeight":592,"y":1466,"frameWidth":576,"frameX":0,"width":576,"frameY":-83,"height":289,"name":"spring0012.png","x":579},{"frameHeight":592,"y":595,"frameWidth":576,"frameX":0,"width":576,"frameY":-62,"height":310,"name":"spring0015.png","x":1},{"frameHeight":592,"y":295,"frameWidth":576,"frameX":0,"width":576,"frameY":-84,"height":288,"name":"spring0011.png","x":2313},{"frameHeight":592,"y":581,"frameWidth":576,"frameX":-42,"width":494,"frameY":-85,"height":268,"name":"spring0005.png","x":2891},{"frameHeight":592,"y":784,"frameWidth":576,"frameX":-99,"width":392,"frameY":-124,"height":159,"name":"spring0001.png","x":2119},{"frameHeight":592,"y":295,"frameWidth":576,"frameX":0,"width":576,"frameY":-22,"height":284,"name":"spring0028.png","x":2891},{"frameHeight":592,"y":295,"frameWidth":576,"frameX":0,"width":576,"frameY":-86,"height":280,"name":"spring0008.png","x":3469},{"frameHeight":592,"y":1,"frameWidth":576,"frameX":0,"width":576,"frameY":-80,"height":292,"name":"spring0024.png","x":579},{"frameHeight":592,"y":1,"frameWidth":576,"frameX":0,"width":576,"frameY":-80,"height":292,"name":"spring0025.png","x":3469},{"frameHeight":592,"y":585,"frameWidth":576,"frameX":-85,"width":421,"frameY":-109,"height":197,"name":"spring0002.png","x":2119},{"frameHeight":592,"y":882,"frameWidth":576,"frameX":0,"width":576,"frameY":-61,"height":291,"name":"spring0026.png","x":579},{"frameHeight":592,"y":295,"frameWidth":576,"frameX":0,"width":576,"frameY":-84,"height":288,"name":"spring0010.png","x":1157},{"frameHeight":592,"y":589,"frameWidth":576,"frameX":0,"width":576,"frameY":-41,"height":291,"name":"spring0027.png","x":579},{"frameHeight":592,"y":907,"frameWidth":576,"frameX":0,"width":576,"frameY":-68,"height":304,"name":"spring0016.png","x":1},{"frameHeight":592,"y":585,"frameWidth":576,"frameX":-50,"width":477,"frameY":-89,"height":255,"name":"spring0006.png","x":1640},{"frameHeight":592,"y":1513,"frameWidth":576,"frameX":0,"width":576,"frameY":-80,"height":292,"name":"spring0018.png","x":1},{"frameHeight":592,"y":1175,"frameWidth":576,"frameX":0,"width":576,"frameY":-83,"height":289,"name":"spring0013.png","x":579}]}